{"graph_name": "fsm_graph_85", "graph_description": "", "umrf_actions": [{"name": "TaManoeuvre", "package_name": "ta_manoeuvre", "description": "Turn left", "id": 0, "effect": "synchronous", "input_parameters": {"direction": {"pvf_type": "string", "pvf_example": "left"}, "verb": {"pvf_type": "string", "pvf_example": "Turn"}}, "children": [{"name": "TaNavigation", "id": 0}]}, {"name": "TaManoeuvre", "package_name": "ta_manoeuvre", "description": "then left", "id": 1, "effect": "synchronous", "input_parameters": {"direction": {"pvf_type": "string", "pvf_example": "left"}, "verb": {"pvf_type": "string", "pvf_example": "turn"}}, "parents": [{"name": "TaManoeuvre", "id": 2}]}, {"name": "TaManoeuvre", "package_name": "ta_manoeuvre", "description": "then turn right", "id": 2, "effect": "synchronous", "input_parameters": {"direction": {"pvf_type": "string", "pvf_example": "right"}, "verb": {"pvf_type": "string", "pvf_example": "turn"}}, "children": [{"name": "TaManoeuvre", "id": 1}], "parents": [{"name": "TaNavigation", "id": 0}]}, {"name": "TaNavigation", "package_name": "ta_navigation", "description": "Go to the wooden table", "id": 0, "effect": "synchronous", "input_parameters": {"location": {"pvf_type": "string", "pvf_example": "to the wooden table"}, "verb": {"pvf_type": "string", "pvf_example": "Go"}}}]}