{"graph_name": "fsm_graph_994", "graph_description": "", "umrf_actions": [{"name": "TaManoeuvre", "package_name": "ta_manoeuvre", "description": "Turn right", "id": 0, "effect": "synchronous", "input_parameters": {"direction": {"pvf_type": "string", "pvf_example": "right"}, "verb": {"pvf_type": "string", "pvf_example": "Turn"}}, "children": [{"name": "TaManoeuvre", "id": 1}]}, {"name": "TaManoeuvre", "package_name": "ta_manoeuvre", "description": "and walk slightly forward to the basketball on the floor.", "id": 1, "effect": "synchronous", "input_parameters": {"direction": {"pvf_type": "string", "pvf_example": "forward"}, "distance": {"amount": {"pvf_type": "number", "pvf_example": "slightly"}, "unit": {"pvf_type": "string"}}, "extent": {"pvf_type": "string", "pvf_example": "to the basketball on the floor"}, "verb": {"pvf_type": "string", "pvf_example": "walk"}}, "parents": [{"name": "TaManoeuvre", "id": 0}]}]}