{
    "name": "TaTransport",
    "package_name": "ta_transport",
    "description": "Bring the clock over to the desk next to the couch",
    "id": 0,
    "effect": "synchronous",
    "input_parameters": {
        "location": {
            "pvf_type": "string",
            "pvf_example": "to the desk next to the couch"
        },
        "object": {
            "pvf_type": "string",
            "pvf_example": "clock"
        },
        "verb": {
            "pvf_type": "string",
            "pvf_example": "Bring"
        }
    }
}