{
    "name": "TaPickup",
    "package_name": "ta_pickup",
    "description": "Pick up the basketball next to the box on the floor",
    "id": 0,
    "effect": "synchronous",
    "input_parameters": {
        "locale": {
            "pvf_type": "string",
            "pvf_example": "next to the box on the floor"
        },
        "object": {
            "pvf_type": "string",
            "pvf_example": "the basketball"
        },
        "verb": {
            "pvf_type": "string",
            "pvf_example": "Pick up"
        }
    }
}